ampho_model/__init__.py
ampho_model/model.py
ampho_model-0.1.dist-info/LICENSE.rst
ampho_model-0.1.dist-info/METADATA
ampho_model-0.1.dist-info/WHEEL
ampho_model-0.1.dist-info/top_level.txt
ampho_model-0.1.dist-info/RECORD
